real_llama_cpp_python-0.1.5.dist-info/.ipynb_checkpoints/requires-checkpoint.txt
real_llamacpp/__init__.py
real_llamacpp/_utils.py
real_llamacpp/model.py
real_llamacpp/test.py
real_llama_cpp_python-0.1.5.dist-info/LICENSE
real_llama_cpp_python-0.1.5.dist-info/METADATA
real_llama_cpp_python-0.1.5.dist-info/WHEEL
real_llama_cpp_python-0.1.5.dist-info/top_level.txt
real_llama_cpp_python-0.1.5.dist-info/RECORD
