Metadata-Version: 2.2
Name: real-llama-cpp-python
Version: 0.1.5
Summary: A simple custom LLM wrapper for llama.cpp with LangChain compatibility.
Home-page: https://github.com/minhtran1309/custom_llm
Author: Minh Tran
Classifier: Programming Language :: Python :: 3
Classifier: License :: OSI Approved :: MIT License
Classifier: Operating System :: OS Independent
Requires-Python: >=3.10
License-File: LICENSE
Requires-Dist: langchain-core
Requires-Dist: pydantic
Dynamic: author
Dynamic: classifier
Dynamic: description
Dynamic: description-content-type
Dynamic: home-page
Dynamic: requires-dist
Dynamic: requires-python
Dynamic: summary
